openunipay/__init__.py
openunipay/admin.py
openunipay/apps.py
openunipay/exceptions.py
openunipay/models.py
openunipay/settings.py
openunipay/urls.py
openunipay/wsgi.py
openunipay/ali_pay/__init__.py
openunipay/ali_pay/admin.py
openunipay/ali_pay/ali_pay_lib.py
openunipay/ali_pay/models.py
openunipay/ali_pay/security.py
openunipay/api/__init__.py
openunipay/api/urls.py
openunipay/api/views_alipay.py
openunipay/api/views_weixin.py
openunipay/management/__init__.py
openunipay/management/commands/__init__.py
openunipay/management/commands/createadminuser.py
openunipay/migrations/0001_initial.py
openunipay/migrations/0002_remove_alipayorder_interface_data.py
openunipay/migrations/0003_auto_20170117_1106.py
openunipay/migrations/0004_weixinqrpayentity_weixinqrpayrecord.py
openunipay/migrations/0005_product.py
openunipay/migrations/0006_auto_20170722_0039.py
openunipay/migrations/__init__.py
openunipay/paygateway/__init__.py
openunipay/paygateway/alipay.py
openunipay/paygateway/unipay.py
openunipay/paygateway/weixin.py
openunipay/util/__init__.py
openunipay/util/datetime.py
openunipay/util/random_helper.py
openunipay/weixin_pay/__init__.py
openunipay/weixin_pay/admin.py
openunipay/weixin_pay/exceptions.py
openunipay/weixin_pay/models.py
openunipay/weixin_pay/qrpay.py
openunipay/weixin_pay/security.py
openunipay/weixin_pay/weixin_pay_lib.py
openunipay/weixin_pay/xml_helper.py
openunipay-0.2.3.dist-info/DESCRIPTION.rst
openunipay-0.2.3.dist-info/METADATA
openunipay-0.2.3.dist-info/RECORD
openunipay-0.2.3.dist-info/WHEEL
openunipay-0.2.3.dist-info/metadata.json
openunipay-0.2.3.dist-info/top_level.txt
