Metadata-Version: 2.0
Name: openunipay
Version: 0.2.3
Summary: openunipay. 统一支付接口. 集成了微信支付、支付宝支付
Home-page: https://github.com/panweifeng/openunipay
Author: Eric Pan
Author-email: pan.weifeng@live.cn
License: MIT
Requires-Dist: django
Requires-Dist: django-cors-headers
Requires-Dist: djangorestframework
Requires-Dist: djangorestframework-xml
Requires-Dist: django-import-export
Requires-Dist: requests
Requires-Dist: rsa
